mkdocs_pages_json_plugin/__init__.py
mkdocs_pages_json_plugin/plugin.py
mkdocs_pages_json_plugin-0.0.2.dist-info/METADATA
mkdocs_pages_json_plugin-0.0.2.dist-info/WHEEL
mkdocs_pages_json_plugin-0.0.2.dist-info/entry_points.txt
mkdocs_pages_json_plugin-0.0.2.dist-info/top_level.txt
mkdocs_pages_json_plugin-0.0.2.dist-info/RECORD
